authentika_client/__init__.py
authentika_client/clients.py
authentika_client/exceptions.py
authentika_client/requests.py
authentika_client/utils.py
authentika_client-0.0.2.dist-info/LICENSE
authentika_client-0.0.2.dist-info/METADATA
authentika_client-0.0.2.dist-info/WHEEL
authentika_client-0.0.2.dist-info/top_level.txt
authentika_client-0.0.2.dist-info/RECORD
